NekUpload/__init__.py
NekUpload/cli.py
NekUpload/index.py
NekUpload/manager.py
NekUpload/testutils.py
NekUpload/NekData/__init__.py
NekUpload/NekData/composite.py
NekUpload/NekData/data_type.py
NekUpload/NekData/expansions.py
NekUpload/NekData/filters.py
NekUpload/NekData/refinements.py
NekUpload/NekData/solver.py
NekUpload/NekData/config/__init__.py
NekUpload/NekData/config/nektar.yaml
NekUpload/NekData/config/nektar_config.py
NekUpload/frontend/__init__.py
NekUpload/frontend/style_guide.py
NekUpload/frontend/assets/explore.png
NekUpload/frontend/assets/help.png
NekUpload/frontend/assets/info.png
NekUpload/frontend/assets/review.png
NekUpload/frontend/assets/settings.png
NekUpload/frontend/assets/upload.png
NekUpload/frontend/components/__init__.py
NekUpload/frontend/components/copyable_table.py
NekUpload/frontend/components/header.py
NekUpload/frontend/components/help.py
NekUpload/frontend/components/menu.py
NekUpload/frontend/components/scrollbox.py
NekUpload/frontend/components/settings_manager.py
NekUpload/frontend/components/terminal.py
NekUpload/frontend/config/__init__.py
NekUpload/frontend/config/db_targets.yaml
NekUpload/frontend/config/settings_loader.py
NekUpload/frontend/scenes/__init__.py
NekUpload/frontend/scenes/explore.py
NekUpload/frontend/scenes/help.py
NekUpload/frontend/scenes/info.py
NekUpload/frontend/scenes/review.py
NekUpload/frontend/scenes/settings.py
NekUpload/frontend/scenes/upload.py
NekUpload/frontend/scenes/upload_widgets/__init__.py
NekUpload/frontend/scenes/upload_widgets/basic.py
NekUpload/frontend/scenes/upload_widgets/create_author_window.py
NekUpload/frontend/scenes/upload_widgets/files.py
NekUpload/frontend/scenes/upload_widgets/geometry.py
NekUpload/frontend/scenes/upload_widgets/output.py
NekUpload/frontend/scenes/upload_widgets/session.py
NekUpload/metadata/__init__.py
NekUpload/metadata/data_types.py
NekUpload/metadata/extractor.py
NekUpload/metadata/identifier.py
NekUpload/metadata/metadata.py
nekupload-1.1.1.dist-info/licenses/LICENSE.txt
nekupload-1.1.1.dist-info/METADATA
nekupload-1.1.1.dist-info/WHEEL
nekupload-1.1.1.dist-info/entry_points.txt
nekupload-1.1.1.dist-info/top_level.txt
nekupload-1.1.1.dist-info/RECORD
